[
    {
        "type": "message",
        "subtype": "channel_join",
        "ts": "1472462862.000004",
        "user": "U25SZC222",
        "text": "<@U25SZC222> has joined the channel"
    },
    {
        "type": "message",
        "subtype": "channel_join",
        "ts": "1472465231.000005",
        "user": "U25T93KF0",
        "text": "<@U25T93KF0> has joined the channel"
    },
    {
        "type": "message",
        "text": "Друзья, Яндекс ищет специалистов, уверенно программирующих на С++ и Python, в команду, которая занимается анализом изображений и видеоконтента, классификацией и генерированием текстов, работает над технологией для создания диалоговых систем. Это вакансия для тех, кто хочет работать с большими объёмами данных, способен генерировать новые идеи и доводить сложные проекты до конца.\n\nВот некоторые из задач, которые мы решаем:\n— Анализ и классификация текста. \n— NLU (natural language understanding) решения.\n— Сегментация и классификация изображений\n— Поиск копий и дубликатов изображений в базе размеров в десятки миллиардов\n— Распознавание текста на изображениях\n— Распознавание лиц\n— Entity2Entity. Определение близости: текста изображению, текста тексту, текста видео и т.д.\n— Развитие и поддержка собственной реализации библиотеки нейронных сетей.\n— Исследования аппаратных платформ (CPU, GPU, FPGA и т.д.) позволяющих максимально эффективно обучать и считать нейронные сети.\n\nТребования:\n* отличная математическая подготовка;\n* знание классических алгоритмов и структур данных;\n* понимание принципов машинного обучения;\n* глубокое понимание и опыт в deep learning;\n* опыт работы с большими объёмами данных;\n* хорошее знание С++ и Python;\n* хорошее владение английским (для чтения технической литературы).\n\nОтдельный плюс — опыт работы с нейросетевыми моделями текстов на естественном языке или с современными технологиями компьютерного зрения.\n\nУ Вас будет возможность:\n— Работать в команде, которая поставляет решения для всего Яндекса (для поиска, для Рекламы, для Диска, для Карт, для переводчика, для Видео и Картинок, для Новостей и т.д.)\n— Делать то, что журналисты и PR называют искусственным интеллектом. \n— Реализовать всю цепочку от научной статьи (или идеи) до запуска функциональности в продакшен.\n— Быть в курсе актуальных научных статей,  проводить различные эксперименты с SOtA решениями. Наши разработчики знают предметную область на уровне ученых.\n\nЭто вам не :levenchuk:, а серьезное дело.\nНа вопросы по вакансии готов ответить <@U07159GKF>",
        "user": "U04BFDYPV",
        "ts": "1472465705.000006",
        "team": "T040HKJE3",
        "user_team": "T040HKJE3",
        "source_team": "T040HKJE3",
        "user_profile": {
            "avatar_hash": "4adf006dce57",
            "image_72": "https:\/\/avatars.slack-edge.com\/2020-04-25\/1084753707173_4adf006dce57cb10e1f7_72.jpg",
            "first_name": "Peter",
            "real_name": "Peter Romov",
            "display_name": "peter",
            "team": "T040HKJE3",
            "name": "peter",
            "is_restricted": false,
            "is_ultra_restricted": false
        },
        "reactions": [
            {
                "name": "muscle",
                "users": [
                    "U0DA4J82H",
                    "U041SH27M",
                    "U07159GKF",
                    "U041P485A",
                    "U041LH06L",
                    "U043J44Q5",
                    "U049HDR2Z",
                    "U040HKJE7",
                    "U0JHK9001",
                    "U1UNFRQ1K",
                    "U1D6DT6HE",
                    "U0952QCHE",
                    "U09JEC7V0",
                    "U070Y25AS",
                    "U1BAQ8W2W",
                    "U1ZAJ4FC4"
                ],
                "count": 16
            },
            {
                "name": "metal",
                "users": [
                    "U041SH27M",
                    "U041P485A",
                    "U041LH06L",
                    "U04ELQZAU",
                    "U064DRUF4",
                    "U1D6DT6HE",
                    "U09JEC7V0",
                    "U070Y25AS"
                ],
                "count": 8
            }
        ]
    },
    {
        "type": "message",
        "text": ":levenchuk: :cry: ",
        "user": "U06J1LG1M",
        "ts": "1472467834.000007",
        "team": "T040HKJE3",
        "user_team": "T040HKJE3",
        "source_team": "T040HKJE3",
        "user_profile": {
            "avatar_hash": "g0f7bbce3713",
            "image_72": "https:\/\/secure.gravatar.com\/avatar\/5e0f7bbce37134d4b0a7a1fe1fc77fa1.jpg?s=72&d=https%3A%2F%2Fa.slack-edge.com%2Fdf10d%2Fimg%2Favatars%2Fava_0022-72.png",
            "first_name": "Pavel",
            "real_name": "Pavel Nesterov",
            "display_name": "mephistopheies",
            "team": "T040HKJE3",
            "name": "mephistopheies",
            "is_restricted": false,
            "is_ultra_restricted": false
        },
        "reactions": [
            {
                "name": "cry",
                "users": [
                    "U0AS548A1",
                    "U049NHC4X",
                    "U0H7VBQQ1",
                    "U0DA4J82H",
                    "U0M39M6LS",
                    "U041LH06L",
                    "U14CTBLFJ",
                    "U040HKJE7",
                    "U1ULNASSV",
                    "U0JHK9001",
                    "U04CH4QBD",
                    "U1GBNAVEK",
                    "U04ELQZAU",
                    "U1YUB0020"
                ],
                "count": 14
            },
            {
                "name": "levenchuk",
                "users": [
                    "U0AS548A1",
                    "U0KPB45TK",
                    "U041SH27M",
                    "U049NHC4X",
                    "U0H7VBQQ1",
                    "U041LH06L",
                    "U14CTBLFJ",
                    "U040HKJE7",
                    "U07V1URT9",
                    "U0JHK9001",
                    "U04CH4QBD",
                    "U1GBNAVEK",
                    "U04ELQZAU",
                    "U1YUB0020"
                ],
                "count": 14
            }
        ]
    },
    {
        "type": "message",
        "subtype": "channel_join",
        "ts": "1472472981.000008",
        "user": "U25U3TU8Y",
        "text": "<@U25U3TU8Y> has joined the channel"
    },
    {
        "type": "message",
        "subtype": "channel_join",
        "ts": "1472473044.000009",
        "user": "U25UF1FAM",
        "text": "<@U25UF1FAM> has joined the channel"
    },
    {
        "type": "message",
        "subtype": "channel_join",
        "ts": "1472473053.000010",
        "user": "U25U1EP52",
        "text": "<@U25U1EP52> has joined the channel"
    },
    {
        "type": "message",
        "subtype": "channel_join",
        "ts": "1472473243.000011",
        "user": "U25UN1AH0",
        "text": "<@U25UN1AH0> has joined the channel"
    },
    {
        "type": "message",
        "subtype": "channel_join",
        "ts": "1472474294.000012",
        "user": "U25U9523Y",
        "text": "<@U25U9523Y> has joined the channel"
    },
    {
        "type": "message",
        "subtype": "channel_join",
        "ts": "1472474415.000013",
        "user": "U25U9M3QW",
        "text": "<@U25U9M3QW> has joined the channel"
    },
    {
        "type": "message",
        "subtype": "channel_join",
        "ts": "1472474582.000014",
        "user": "U25ULGHQF",
        "text": "<@U25ULGHQF> has joined the channel"
    },
    {
        "type": "message",
        "subtype": "channel_join",
        "ts": "1472475014.000015",
        "user": "U25UPSERX",
        "text": "<@U25UPSERX> has joined the channel"
    },
    {
        "type": "message",
        "subtype": "channel_join",
        "ts": "1472478049.000016",
        "user": "U25V775B3",
        "text": "<@U25V775B3> has joined the channel"
    },
    {
        "type": "message",
        "text": "Вакансия: \nАзбука вкуса, ищет самого базового аналитика. \nЗадачи простые, сложных не дадут((.. Но если много интузиазма, то можно самому придумать чем занятся, ибо данных у ритейла полно). Кто ищет с чего начать, пишите в личку :face_with_rolling_eyes:",
        "user": "U071HGRL5",
        "ts": "1472480192.000020",
        "team": "T040HKJE3",
        "user_team": "T040HKJE3",
        "source_team": "T040HKJE3",
        "user_profile": {
            "avatar_hash": "fe374b3b56fd",
            "image_72": "https:\/\/avatars.slack-edge.com\/2016-05-05\/40436033649_fe374b3b56fd619f0bfc_72.jpg",
            "first_name": "Андрей",
            "real_name": "Андрей Котов",
            "display_name": "andrey.kotov.a",
            "team": "T040HKJE3",
            "name": "andrey.kotov.a",
            "is_restricted": false,
            "is_ultra_restricted": false
        },
        "reactions": [
            {
                "name": "moneybag",
                "users": [
                    "U14CTBLFJ",
                    "U1D6DT6HE",
                    "U1GBNAVEK",
                    "U065VP6F7",
                    "U0DA4J82H"
                ],
                "count": 5
            }
        ]
    },
    {
        "type": "message",
        "text": "чето не очень заманчиво",
        "user": "U0DA4J82H",
        "ts": "1472480225.000021",
        "team": "T040HKJE3",
        "user_team": "T040HKJE3",
        "source_team": "T040HKJE3",
        "user_profile": {
            "avatar_hash": "gec7013c3d5b",
            "image_72": "https:\/\/secure.gravatar.com\/avatar\/28ec7013c3d5b5cbd9633d12c1407eff.jpg?s=72&d=https%3A%2F%2Fa.slack-edge.com%2Fdf10d%2Fimg%2Favatars%2Fava_0003-72.png",
            "first_name": "Алексей",
            "real_name": "Алексей Ололоев",
            "display_name": "ololo",
            "team": "T040HKJE3",
            "name": "ololo",
            "is_restricted": false,
            "is_ultra_restricted": false
        }
    },
    {
        "type": "message",
        "text": "после яндекса )",
        "user": "U0DA4J82H",
        "ts": "1472480242.000022",
        "team": "T040HKJE3",
        "user_team": "T040HKJE3",
        "source_team": "T040HKJE3",
        "user_profile": {
            "avatar_hash": "gec7013c3d5b",
            "image_72": "https:\/\/secure.gravatar.com\/avatar\/28ec7013c3d5b5cbd9633d12c1407eff.jpg?s=72&d=https%3A%2F%2Fa.slack-edge.com%2Fdf10d%2Fimg%2Favatars%2Fava_0003-72.png",
            "first_name": "Алексей",
            "real_name": "Алексей Ололоев",
            "display_name": "ololo",
            "team": "T040HKJE3",
            "name": "ololo",
            "is_restricted": false,
            "is_ultra_restricted": false
        }
    },
    {
        "type": "message",
        "text": "<@U0DA4J82H> не пойдешь?",
        "user": "U09JEC7V0",
        "ts": "1472480243.000023",
        "team": "T040HKJE3",
        "user_team": "T040HKJE3",
        "source_team": "T040HKJE3",
        "user_profile": {
            "avatar_hash": "6dff5bc996df",
            "image_72": "https:\/\/avatars.slack-edge.com\/2015-11-06\/14021186960_6dff5bc996df9341fb00_72.jpg",
            "first_name": "Sergey",
            "real_name": "Sergey Sviridov",
            "display_name": "ssviridov",
            "team": "T040HKJE3",
            "name": "ssviridov",
            "is_restricted": false,
            "is_ultra_restricted": false
        }
    },
    {
        "type": "message",
        "text": "задачи везде простые) просто не все об этом пишут",
        "user": "U0DA4J82H",
        "ts": "1472480264.000024",
        "team": "T040HKJE3",
        "user_team": "T040HKJE3",
        "source_team": "T040HKJE3",
        "user_profile": {
            "avatar_hash": "gec7013c3d5b",
            "image_72": "https:\/\/secure.gravatar.com\/avatar\/28ec7013c3d5b5cbd9633d12c1407eff.jpg?s=72&d=https%3A%2F%2Fa.slack-edge.com%2Fdf10d%2Fimg%2Favatars%2Fava_0003-72.png",
            "first_name": "Алексей",
            "real_name": "Алексей Ололоев",
            "display_name": "ololo",
            "team": "T040HKJE3",
            "name": "ololo",
            "is_restricted": false,
            "is_ultra_restricted": false
        }
    },
    {
        "type": "message",
        "text": "ну не везде, но много где",
        "user": "U0DA4J82H",
        "ts": "1472480273.000025",
        "team": "T040HKJE3",
        "user_team": "T040HKJE3",
        "source_team": "T040HKJE3",
        "user_profile": {
            "avatar_hash": "gec7013c3d5b",
            "image_72": "https:\/\/secure.gravatar.com\/avatar\/28ec7013c3d5b5cbd9633d12c1407eff.jpg?s=72&d=https%3A%2F%2Fa.slack-edge.com%2Fdf10d%2Fimg%2Favatars%2Fava_0003-72.png",
            "first_name": "Алексей",
            "real_name": "Алексей Ололоев",
            "display_name": "ololo",
            "team": "T040HKJE3",
            "name": "ololo",
            "is_restricted": false,
            "is_ultra_restricted": false
        }
    },
    {
        "type": "message",
        "text": "Азбука вкуса наверняка молодая и активно развивающаяся, надо добавить )",
        "user": "U0DA4J82H",
        "ts": "1472480346.000026",
        "team": "T040HKJE3",
        "user_team": "T040HKJE3",
        "source_team": "T040HKJE3",
        "user_profile": {
            "avatar_hash": "gec7013c3d5b",
            "image_72": "https:\/\/secure.gravatar.com\/avatar\/28ec7013c3d5b5cbd9633d12c1407eff.jpg?s=72&d=https%3A%2F%2Fa.slack-edge.com%2Fdf10d%2Fimg%2Favatars%2Fava_0003-72.png",
            "first_name": "Алексей",
            "real_name": "Алексей Ололоев",
            "display_name": "ololo",
            "team": "T040HKJE3",
            "name": "ololo",
            "is_restricted": false,
            "is_ultra_restricted": false
        }
    },
    {
        "type": "message",
        "text": "ладно, прекращаю флуд",
        "user": "U0DA4J82H",
        "ts": "1472480357.000027",
        "team": "T040HKJE3",
        "user_team": "T040HKJE3",
        "source_team": "T040HKJE3",
        "user_profile": {
            "avatar_hash": "gec7013c3d5b",
            "image_72": "https:\/\/secure.gravatar.com\/avatar\/28ec7013c3d5b5cbd9633d12c1407eff.jpg?s=72&d=https%3A%2F%2Fa.slack-edge.com%2Fdf10d%2Fimg%2Favatars%2Fava_0003-72.png",
            "first_name": "Алексей",
            "real_name": "Алексей Ололоев",
            "display_name": "ololo",
            "team": "T040HKJE3",
            "name": "ololo",
            "is_restricted": false,
            "is_ultra_restricted": false
        }
    },
    {
        "type": "message",
        "text": "впрочем, а АБ  всякие печеньки\\фрукты из своих закромов в офисе держит?)",
        "user": "U040HKJE7",
        "ts": "1472480461.000028",
        "team": "T040HKJE3",
        "user_team": "T040HKJE3",
        "source_team": "T040HKJE3",
        "user_profile": {
            "avatar_hash": "910ffe66f361",
            "image_72": "https:\/\/avatars.slack-edge.com\/2017-12-25\/291044574499_910ffe66f3612ed5c505_72.jpg",
            "first_name": "Alex",
            "real_name": "Alex Natekin",
            "display_name": "natekin",
            "team": "T040HKJE3",
            "name": "natekin",
            "is_restricted": false,
            "is_ultra_restricted": false
        }
    },
    {
        "type": "message",
        "text": "...хотел развить тему \"работать за еду\"",
        "user": "U040HKJE7",
        "ts": "1472480478.000029",
        "team": "T040HKJE3",
        "user_team": "T040HKJE3",
        "source_team": "T040HKJE3",
        "user_profile": {
            "avatar_hash": "910ffe66f361",
            "image_72": "https:\/\/avatars.slack-edge.com\/2017-12-25\/291044574499_910ffe66f3612ed5c505_72.jpg",
            "first_name": "Alex",
            "real_name": "Alex Natekin",
            "display_name": "natekin",
            "team": "T040HKJE3",
            "name": "natekin",
            "is_restricted": false,
            "is_ultra_restricted": false
        }
    },
    {
        "type": "message",
        "text": "<@U1UM6S9KN>: на странице стажировок Яндекса раскрыто ",
        "user": "U0AS548A1",
        "ts": "1472480624.000033",
        "team": "T040HKJE3",
        "user_team": "T040HKJE3",
        "source_team": "T040HKJE3",
        "user_profile": {
            "avatar_hash": "g493c194e4ec",
            "image_72": "https:\/\/secure.gravatar.com\/avatar\/12493c194e4ec990924dedf0a6d04d5e.jpg?s=72&d=https%3A%2F%2Fa.slack-edge.com%2Fdf10d%2Fimg%2Favatars%2Fava_0026-72.png",
            "first_name": "kek",
            "real_name": "kek",
            "display_name": "iesh00a",
            "team": "T040HKJE3",
            "name": "evgeniiegorov",
            "is_restricted": false,
            "is_ultra_restricted": false
        }
    },
    {
        "type": "message",
        "text": "<@U071HGRL5>: насколько я помню, в Азбуке вкуса Navision в качестве одной из учётных систем. Знание НАВа дополнительные плюшки даёт?",
        "user": "U1YJL9Q8Z",
        "ts": "1472493213.000038",
        "team": "T040HKJE3",
        "user_team": "T040HKJE3",
        "source_team": "T040HKJE3",
        "user_profile": {
            "avatar_hash": "6dd6257cb2a5",
            "image_72": "https:\/\/avatars.slack-edge.com\/2017-10-09\/253725822628_6dd6257cb2a5a663fae2_72.jpg",
            "first_name": "Konstantin",
            "real_name": "Konstantin Ivanin",
            "display_name": "const",
            "team": "T040HKJE3",
            "name": "const",
            "is_restricted": false,
            "is_ultra_restricted": false
        },
        "reactions": [
            {
                "name": "r",
                "users": [
                    "U14CTBLFJ"
                ],
                "count": 1
            }
        ]
    },
    {
        "type": "message",
        "subtype": "channel_join",
        "ts": "1472496292.000039",
        "user": "U263V3XR8",
        "text": "<@U263V3XR8> has joined the channel"
    },
    {
        "type": "message",
        "subtype": "channel_join",
        "ts": "1472499916.000040",
        "user": "U262NSHCK",
        "text": "<@U262NSHCK> has joined the channel"
    },
    {
        "type": "message",
        "text": "<@U07159GKF> это какого уровня вакансия? Junior\/Middle\/Senior?",
        "user": "U11ATF3GR",
        "ts": "1472534093.000041",
        "team": "T040HKJE3",
        "user_team": "T040HKJE3",
        "source_team": "T040HKJE3",
        "user_profile": {
            "avatar_hash": "d9fc6be1dbdf",
            "image_72": "https:\/\/avatars.slack-edge.com\/2016-07-04\/56738576769_d9fc6be1dbdf989043c2_72.jpg",
            "first_name": "Евгений",
            "real_name": "Евгений Елтышев",
            "display_name": "evgeny_eltyshev",
            "team": "T040HKJE3",
            "name": "evgeny_eltyshev",
            "is_restricted": false,
            "is_ultra_restricted": false
        },
        "reactions": [
            {
                "name": "eyes",
                "users": [
                    "U0AS548A1",
                    "U11ATF3GR"
                ],
                "count": 2
            }
        ]
    },
    {
        "type": "message",
        "text": "Азбука Вкуса — это вакансия уровня Premium :slightly_smiling_face:",
        "user": "U0JKYTE4B",
        "ts": "1472537669.000042",
        "team": "T040HKJE3",
        "user_team": "T040HKJE3",
        "source_team": "T040HKJE3",
        "user_profile": {
            "avatar_hash": "3d6641a379dd",
            "image_72": "https:\/\/avatars.slack-edge.com\/2020-09-30\/1403130875956_3d6641a379dd5c317d0b_72.jpg",
            "first_name": "Ivan",
            "real_name": "Ivan Khvostishkov",
            "display_name": "ivan.khvostishkov",
            "team": "T040HKJE3",
            "name": "ivan.khvostishkov",
            "is_restricted": false,
            "is_ultra_restricted": false
        },
        "edited": {
            "user": "U0JKYTE4B",
            "ts": "1472537691.000000"
        },
        "reactions": [
            {
                "name": "povar",
                "users": [
                    "U0DA4J82H",
                    "U09JEC7V0",
                    "U15UZGX9A",
                    "U1G303UTW",
                    "U041SH27M",
                    "U04CH4QBD",
                    "U04ELQZAU",
                    "U040HKJE7",
                    "U14BPHDK6",
                    "U054DU76Y",
                    "U1GMCNV3M",
                    "U0AGVBP6U",
                    "U0MEP6PT2"
                ],
                "count": 13
            },
            {
                "name": "facepalm",
                "users": [
                    "U1CF4A6BT"
                ],
                "count": 1
            }
        ]
    },
    {
        "type": "message",
        "text": "<@U0JKYTE4B>: Аха-ха))) напомню что премиум у них магазины, в не компания(.. \n\n<@U040HKJE7> к сожалению там не кормят пармезаном(.. Да и соц пакет скудный. Если и работать за еду, то идти в Mars шоколадный!!! Не путать с Mars Petcare.. \n\n<@U1YJL9Q8Z> на счет программ не уточнял.. Позиция базовая, тут экселя достаточно). Преимущество будет, разве что в знаниях демандтека от IBM, но третий и последний человек, кто с ним знаком в России, это я и это не особо предмет для гордости.. ",
        "user": "U071HGRL5",
        "ts": "1472538139.000044",
        "team": "T040HKJE3",
        "user_team": "T040HKJE3",
        "source_team": "T040HKJE3",
        "user_profile": {
            "avatar_hash": "fe374b3b56fd",
            "image_72": "https:\/\/avatars.slack-edge.com\/2016-05-05\/40436033649_fe374b3b56fd619f0bfc_72.jpg",
            "first_name": "Андрей",
            "real_name": "Андрей Котов",
            "display_name": "andrey.kotov.a",
            "team": "T040HKJE3",
            "name": "andrey.kotov.a",
            "is_restricted": false,
            "is_ultra_restricted": false
        },
        "reactions": [
            {
                "name": "noexcel",
                "users": [
                    "U0E2W4VKL",
                    "U04ELQZAU",
                    "U1ULNASSV",
                    "U1J56K7RA"
                ],
                "count": 4
            }
        ]
    },
    {
        "type": "message",
        "text": "Что-то так себе реклама для вакансии",
        "user": "U0DA4J82H",
        "ts": "1472538281.000045",
        "team": "T040HKJE3",
        "user_team": "T040HKJE3",
        "source_team": "T040HKJE3",
        "user_profile": {
            "avatar_hash": "gec7013c3d5b",
            "image_72": "https:\/\/secure.gravatar.com\/avatar\/28ec7013c3d5b5cbd9633d12c1407eff.jpg?s=72&d=https%3A%2F%2Fa.slack-edge.com%2Fdf10d%2Fimg%2Favatars%2Fava_0003-72.png",
            "first_name": "Алексей",
            "real_name": "Алексей Ололоев",
            "display_name": "ololo",
            "team": "T040HKJE3",
            "name": "ololo",
            "is_restricted": false,
            "is_ultra_restricted": false
        },
        "reactions": [
            {
                "name": "joy",
                "users": [
                    "U09JEC7V0",
                    "U1MLEMG11",
                    "U041SH27M",
                    "U04ELQZAU",
                    "U041LH06L",
                    "U1ULNASSV",
                    "U040HKJE7",
                    "U1CMPEWPQ"
                ],
                "count": 8
            },
            {
                "name": "moneybag",
                "users": [
                    "U14CTBLFJ"
                ],
                "count": 1
            }
        ]
    }
]