[
    {
        "type": "message",
        "text": "<https:\/\/opendatascience.slack.com\/archives\/C04DA5FUF\/p1514290045000165?thread_ts=1514287667.000141&amp;cid=C04DA5FUF>\n<https:\/\/opendatascience.slack.com\/archives\/C04DA5FUF\/p1514288394000088?thread_ts=1514287667.000141&amp;cid=C04DA5FUF>\nДействительно, :be-a-man: ! Было бы интересно в <#C0SGCGB52|career> почитать длинную историю о том, как проходили одно или несколько интервью на эту вакансию.",
        "user": "U27HU84H4",
        "ts": "1514362473.000062",
        "team": "T040HKJE3",
        "user_team": "T040HKJE3",
        "source_team": "T040HKJE3",
        "user_profile": {
            "avatar_hash": "7ec7ef7154ba",
            "image_72": "https:\/\/avatars.slack-edge.com\/2018-04-26\/354236189286_7ec7ef7154baf1b9e9b5_72.jpg",
            "first_name": "Leonid",
            "real_name": "Leonid Sinev",
            "display_name": "leonid",
            "team": "T040HKJE3",
            "name": "leonid",
            "is_restricted": false,
            "is_ultra_restricted": false
        },
        "attachments": [
            {
                "from_url": "https:\/\/opendatascience.slack.com\/archives\/C04DA5FUF\/p1514290045000165?thread_ts=1514287667.000141&amp;cid=C04DA5FUF",
                "fallback": "[December 26th, 2017 4:07 AM] amber4eg: Польза, кстати, была бы, если бы та написал в сюда или в карьеру \"вот по этой ссылке вакансия, на самом деле эти `лидеры рынка` - это РосТудаСюдас, вилка у них 150-200\"",
                "ts": "1514290045.000165",
                "author_id": "U4WM1939Q",
                "author_subname": "Andrey Gurevich",
                "channel_id": "C04DA5FUF",
                "channel_name": "_jobs",
                "is_msg_unfurl": true,
                "is_reply_unfurl": true,
                "text": "Польза, кстати, была бы, если бы та написал в сюда или в карьеру \"вот по этой ссылке вакансия, на самом деле эти `лидеры рынка` - это РосТудаСюдас, вилка у них 150-200\"",
                "author_name": "Andrey Gurevich",
                "author_link": "https:\/\/opendatascience.slack.com\/team\/U4WM1939Q",
                "author_icon": "https:\/\/avatars.slack-edge.com\/2017-09-16\/242353084725_586abf0ae10da1c590ec_48.jpg",
                "mrkdwn_in": [
                    "text"
                ],
                "id": 1,
                "footer": "From a thread in #_jobs"
            },
            {
                "from_url": "https:\/\/opendatascience.slack.com\/archives\/C04DA5FUF\/p1514288394000088?thread_ts=1514287667.000141&amp;cid=C04DA5FUF",
                "fallback": "[December 26th, 2017 3:39 AM] lange_am: От одной из этих вакансий у меня даже есть офер :slightly_smiling_face: Они меня находили сами. Пусть и другие посмотрят.",
                "ts": "1514288394.000088",
                "author_id": "U0H8RU34N",
                "author_subname": "Andrey Lange",
                "channel_id": "C04DA5FUF",
                "channel_name": "_jobs",
                "is_msg_unfurl": true,
                "is_reply_unfurl": true,
                "text": "От одной из этих вакансий у меня даже есть офер :slightly_smiling_face: Они меня находили сами. Пусть и другие посмотрят.",
                "author_name": "Andrey Lange",
                "author_link": "https:\/\/opendatascience.slack.com\/team\/U0H8RU34N",
                "author_icon": "https:\/\/avatars.slack-edge.com\/2015-12-26\/17404364916_85836cba58b8ec1221df_48.jpg",
                "mrkdwn_in": [
                    "text"
                ],
                "id": 2,
                "footer": "From a thread in #_jobs"
            }
        ],
        "thread_ts": "1514287667.000141",
        "parent_user_id": "U0H8RU34N"
    },
    {
        "type": "message",
        "text": "1. Я не рекрутер, меня попросили.\n2. К тексту вакансии я сам вписал ЗП заявленную для меня отдельно от рекрутера, чтобы выполнить требования канала\n3. Тут раньше просили, чтобы были не ссылки а текст - я вставил текст + ЗП\n4. Поскольку это не длинная история, а конкретные вакансии,  то поместил их в этот канал, а не в <#C0SGCGB52|career>.\n5. Предлагал и предлагаю вынести вакансии не от самих участников сообщества в отдельное место. Раз организаторы ODS против - значит места не будет.",
        "user": "U0H8RU34N",
        "ts": "1514363400.000156",
        "team": "T040HKJE3",
        "user_team": "T040HKJE3",
        "source_team": "T040HKJE3",
        "user_profile": {
            "avatar_hash": "85836cba58b8",
            "image_72": "https:\/\/avatars.slack-edge.com\/2015-12-26\/17404364916_85836cba58b8ec1221df_72.jpg",
            "first_name": "Andrey",
            "real_name": "Andrey Lange",
            "display_name": "lange_am",
            "team": "T040HKJE3",
            "name": "lange_am",
            "is_restricted": false,
            "is_ultra_restricted": false
        },
        "thread_ts": "1514287667.000141",
        "parent_user_id": "U0H8RU34N"
    },
    {
        "type": "message",
        "text": "6. Вообще не качаю права.",
        "user": "U0H8RU34N",
        "ts": "1514364701.000172",
        "team": "T040HKJE3",
        "user_team": "T040HKJE3",
        "source_team": "T040HKJE3",
        "user_profile": {
            "avatar_hash": "85836cba58b8",
            "image_72": "https:\/\/avatars.slack-edge.com\/2015-12-26\/17404364916_85836cba58b8ec1221df_72.jpg",
            "first_name": "Andrey",
            "real_name": "Andrey Lange",
            "display_name": "lange_am",
            "team": "T040HKJE3",
            "name": "lange_am",
            "is_restricted": false,
            "is_ultra_restricted": false
        },
        "thread_ts": "1514287667.000141",
        "parent_user_id": "U0H8RU34N"
    },
    {
        "type": "message",
        "text": "7. Права ограничены пунктами:\n-название вакансии;\n-город\n-описание того что нужно делать;\n-требования к кандидатам;\n-вилка зарплат (от и до) (крайне желательна)",
        "user": "U0H8RU34N",
        "ts": "1514364995.000261",
        "team": "T040HKJE3",
        "user_team": "T040HKJE3",
        "source_team": "T040HKJE3",
        "user_profile": {
            "avatar_hash": "85836cba58b8",
            "image_72": "https:\/\/avatars.slack-edge.com\/2015-12-26\/17404364916_85836cba58b8ec1221df_72.jpg",
            "first_name": "Andrey",
            "real_name": "Andrey Lange",
            "display_name": "lange_am",
            "team": "T040HKJE3",
            "name": "lange_am",
            "is_restricted": false,
            "is_ultra_restricted": false
        },
        "thread_ts": "1514287667.000141",
        "parent_user_id": "U0H8RU34N"
    },
    {
        "type": "message",
        "text": "Неплохо бы в правила добавить название компании, в которой надо будет работать",
        "user": "U60EETE7N",
        "ts": "1514378748.000049",
        "team": "T040HKJE3",
        "user_team": "T040HKJE3",
        "source_team": "T040HKJE3",
        "user_profile": {
            "avatar_hash": "f7e6a648a94b",
            "image_72": "https:\/\/avatars.slack-edge.com\/2019-06-17\/660704542257_f7e6a648a94bf14f6db6_72.jpg",
            "first_name": "sergey",
            "real_name": "sergey zakharov",
            "display_name": "sergei3000",
            "team": "T040HKJE3",
            "name": "sergei3000",
            "is_restricted": false,
            "is_ultra_restricted": false
        },
        "thread_ts": "1514287667.000141",
        "parent_user_id": "U0H8RU34N",
        "reactions": [
            {
                "name": "heavy_plus_sign",
                "users": [
                    "U4WM1939Q",
                    "U7F3QDMNK",
                    "U34Q3KU8H",
                    "U10K3LXHV",
                    "U15UZGX9A",
                    "U0L4KM9R9",
                    "U44CT68FP"
                ],
                "count": 7
            }
        ]
    },
    {
        "type": "message",
        "text": "И адрес",
        "user": "U4WM1939Q",
        "ts": "1514379471.000111",
        "team": "T040HKJE3",
        "user_team": "T040HKJE3",
        "source_team": "T040HKJE3",
        "user_profile": {
            "avatar_hash": "586abf0ae10d",
            "image_72": "https:\/\/avatars.slack-edge.com\/2017-09-16\/242353084725_586abf0ae10da1c590ec_72.jpg",
            "first_name": "Andrey",
            "real_name": "Andrey Gurevich",
            "display_name": "amber4eg",
            "team": "T040HKJE3",
            "name": "amber4eg",
            "is_restricted": false,
            "is_ultra_restricted": false
        },
        "thread_ts": "1514287667.000141",
        "parent_user_id": "U0H8RU34N"
    }
]