[
    {
        "client_msg_id": "9dd40db1-3cec-4b2c-b4c6-5342fba61e0b",
        "type": "message",
        "text": "Привет, коллеги\nВакансия: *Senior Data Scientist (NLP)*\nКомпания: *P1K*\nГород: *Киев* (м. Почайная, офис возле ТРЦ Блокбастер, есть развозка или около 20 мин. пешком)\nВилка: *3000-5000$*\n\nКо мне в R&amp;D команду P1K, на проект связанный с извлечением знаний из юридической документации (тексты на английском), требуется Senior Data Scientist с уклоном в NLP.\n\n*Что нужно будет делать:*\nУ нас есть первый MVP проекта, умеющего делать базовую обработку юридических договоров. На первом этапе нужно будет добавить к существующему прототипу новые функции, возможно доработать что-то из старых и выкатить следующий MVP. Далее создавать новые функции, возможно, участвовать в презентациях решения клиентам и делать проект умнее, используя ML.\n\nИсходно вы будете работать в моей команде, по мере развития продукта под него будет сформирована отдельная команда, куда вы и перейдете. Продукт новый, нерешенных задач много, есть простор для реализации своих идей и новых подходов.\n\nВ данный момент самое важное – быстро добавлять новые функции в MVP, поэтому, первое время нужно будет использовать готовые решения, библиотеки и техники NLP, на более поздних этапах появится возможность разметить данные и заняться больше ML задачами – начиная с retrain существующих решений под наш датасет и далее построения классических и Deep Learning models.\n\nЧеловек должен быть способен самостоятельно завернуть полученное решение и добавить его в прототип (сейчас это Flask), при необходимости, переписать этот прототип. С другой стороны, позиция предусматривает высокий уровень самостоятельности – в идеале, человек должен быть способен оценить трудоемкость и реализуемость новых функций, предложить подходы к реализации, предсказать ориентировочную точность предлагаемых подходов и потенциальные проблемы.\n\n*Необходимые навыки:*\n— 4+ years of experience in NLP\n— Ability to build MVP fast\n— Experience in using Python to solve NLP tasks\n— Experience in using Deep Learning for NLP\n— Experience in using general libraries for data processing\/analysis: matplotlib\/seaborn (or analogs), pandas, numpy.\n— Strong knowledge of regular expressions\n— Strong knowledge of modern libraries for language processing (primarily English): NLTK, spaCy, Gensim.\n— Knowledge of text vectorization methods (tf\/idf, word2vec) and standard libraries (FastText, BERT or analogs).\n— Knowledge of Information Extraction methods (NER, terminology extraction, keywords extraction, etc.).\n— Knowledge of classical machine learning algorithms and libraries: sklearn (regression, trees, SVM, ensembles) and experience in their application to solve NLP issues.\n— Unsupervised learning: different clustering algorithms, SVD, LDA.\n— Ability to build simple prototypes on Flask.\n\n*Будет плюсом:*\n— Experience with Git\n— Experience with SQL\n— Keras \/ Tensorflow \/ PyTorch\n— Experience with Cloud based solutions for NLP (API usage)\n— Experience with Amazon AWS.\n\n\nЕсли вы Senior++ и вилка вам мала – все-равно приходите, если вы нам идеально подойдете, то вилка не проблема.\nЕсли вы Strong Middle и обладаете большей частью из перечисленных навыков – тоже приходите, возможно, мы подойдем друг другу.\n\nРезюме присылайте напрямую мне: <mailto:a.nikonenko@p1k.co.uk|a.nikonenko@p1k.co.uk> обойдемся без HR, встретимся у нас в офисе, поговорим.\n\nЕсли остались вопросы – велкам в комментарии или пишите в личку.",
        "user": "U6H12P4M7",
        "ts": "1572683617.465000",
        "team": "T040HKJE3",
        "user_team": "T040HKJE3",
        "source_team": "T040HKJE3",
        "user_profile": {
            "avatar_hash": "c80ab5e3b6c4",
            "image_72": "https:\/\/avatars.slack-edge.com\/2019-11-02\/806302162178_c80ab5e3b6c4a4611c20_72.png",
            "first_name": "Andrey",
            "real_name": "Andrey Nikonenko",
            "display_name": "andrew.n",
            "team": "T040HKJE3",
            "name": "andrew.n",
            "is_restricted": false,
            "is_ultra_restricted": false
        },
        "thread_ts": "1572683617.465000",
        "reply_count": 2,
        "reply_users_count": 2,
        "latest_reply": "1572788235.496900",
        "reply_users": [
            "UC7DFDJUA",
            "U6H12P4M7"
        ],
        "replies": [
            {
                "user": "UC7DFDJUA",
                "ts": "1572703665.474700"
            },
            {
                "user": "U6H12P4M7",
                "ts": "1572788235.496900"
            }
        ],
        "subscribed": false,
        "reactions": [
            {
                "name": "notbad",
                "users": [
                    "UB4AGRL3C",
                    "U8DEZV7E2",
                    "U7SFPUVQF",
                    "UE61U6DCL",
                    "U7N4E8GBF",
                    "U24FHECDD",
                    "U4B8MC0AD",
                    "U30LWK54N",
                    "U9KDY2PM2",
                    "U93P65UQN",
                    "UPD47KCSZ",
                    "U1LNJJWRG",
                    "U3Z5KPTRQ",
                    "U8PMZ6397",
                    "UELA14HSS",
                    "UDTFQJN1M",
                    "UFH4MATMY",
                    "U6Z21KSBC",
                    "U24N3AB96",
                    "UC9HBTUKG",
                    "U50EVF538",
                    "UGFMUV1UH",
                    "ULF96QF3K",
                    "U4N7G9RQA",
                    "UGVJEKKB8",
                    "U8R7BEGUU",
                    "U2AJE72Q6",
                    "UDFFEC1B3"
                ],
                "count": 28
            },
            {
                "name": "+1",
                "users": [
                    "U8DEZV7E2",
                    "U0K47J3HR",
                    "U7N4E8GBF",
                    "U24FHECDD",
                    "U30LWK54N",
                    "U93P65UQN",
                    "U3Z5KPTRQ",
                    "UJW9M71RV",
                    "U8PMZ6397",
                    "U27SUBTB9",
                    "UPNPXHPU5",
                    "U8SRKP9U3",
                    "U4LCAKK8C",
                    "U8R7BEGUU",
                    "U2AJE72Q6",
                    "U4DV4LYK1"
                ],
                "count": 16
            },
            {
                "name": "flag-ua",
                "users": [
                    "UNMTRMDE0",
                    "UMZ4KE98F",
                    "UPX5BSYLF",
                    "UGDCT6ZR7",
                    "UELA14HSS",
                    "UFH4MATMY",
                    "U8X231ZA6",
                    "UGFMUV1UH",
                    "UL2QDC909",
                    "U27SUBTB9",
                    "U4N7G9RQA",
                    "UC7DFDJUA",
                    "UCFU0F4CQ",
                    "UNEAGQVHC",
                    "U8SRKP9U3",
                    "U5GHLLL2D",
                    "U8R7BEGUU"
                ],
                "count": 17
            },
            {
                "name": "widefork",
                "users": [
                    "U9ZMU4630",
                    "UC7DFDJUA"
                ],
                "count": 2
            },
            {
                "name": "moneybag",
                "users": [
                    "U09NJCK3K"
                ],
                "count": 1
            }
        ]
    },
    {
        "client_msg_id": "2ff18c0a-efa9-43b6-81cd-cf7dc165b300",
        "type": "message",
        "text": "Аналитикам мы предлагаем хорошо. Это аналитик с годом опыта работы.",
        "user": "U43QVTY49",
        "ts": "1572688823.470300",
        "team": "T040HKJE3",
        "user_team": "T040HKJE3",
        "source_team": "T040HKJE3",
        "user_profile": {
            "avatar_hash": "e478d3302d4c",
            "image_72": "https:\/\/avatars.slack-edge.com\/2020-04-09\/1046324740519_e478d3302d4c1bc1bf52_72.jpg",
            "first_name": "Pavel",
            "real_name": "Pavel Myagkikh",
            "display_name": "pavel_myagkikh",
            "team": "T040HKJE3",
            "name": "pavel_myagkikh",
            "is_restricted": false,
            "is_ultra_restricted": false
        },
        "edited": {
            "user": "U43QVTY49",
            "ts": "1572688831.000000"
        },
        "thread_ts": "1572642441.443400",
        "parent_user_id": "U43QVTY49",
        "reactions": [
            {
                "name": "coolstorybob",
                "users": [
                    "U9V48C738",
                    "UC7F3KJ7P",
                    "UE0KXG49J",
                    "UCKGAQKE0",
                    "UPWJZKUB1"
                ],
                "count": 5
            },
            {
                "name": "+1",
                "users": [
                    "UGDUCRYJ0"
                ],
                "count": 1
            }
        ]
    },
    {
        "client_msg_id": "da23e8f9-bf74-4f4b-a6ff-f7ada5f6d843",
        "type": "message",
        "text": "А почему вилка на доу 5-7, а тут 3-5?\n<https:\/\/jobs.dou.ua\/companies\/p1k\/vacancies\/106912\/>",
        "user": "UC7DFDJUA",
        "ts": "1572703665.474700",
        "team": "T040HKJE3",
        "user_team": "T040HKJE3",
        "source_team": "T040HKJE3",
        "user_profile": {
            "avatar_hash": "9f4706c42628",
            "image_72": "https:\/\/avatars.slack-edge.com\/2020-11-29\/1529072651142_9f4706c42628beeeb46f_72.png",
            "first_name": "Mykola",
            "real_name": "Mykola Lukashchuk",
            "display_name": "Nicolas",
            "team": "T040HKJE3",
            "name": "nikoobos",
            "is_restricted": false,
            "is_ultra_restricted": false
        },
        "attachments": [
            {
                "service_name": "ДОУ",
                "title": "Senior Data Scientist (NLP)",
                "title_link": "https:\/\/jobs.dou.ua\/companies\/p1k\/vacancies\/106912\/",
                "text": "- 4+ years of experience in NLP - Ability to build MVP fast - Experience in using Python to solve NLP issues - Experience in using Deep Learning for NLP - Experience in using general libraries for data processing: matplotlib\/seaborn (or analogs), pandas,...",
                "fallback": "ДОУ: Senior Data Scientist (NLP)",
                "thumb_url": "https:\/\/s.dou.ua\/CACHE\/images\/img\/static\/companies\/DOU_White\/0b6c8962acc85ceb0067f06fceec293e.png",
                "from_url": "https:\/\/jobs.dou.ua\/companies\/p1k\/vacancies\/106912\/",
                "thumb_width": 202,
                "thumb_height": 202,
                "service_icon": "https:\/\/s.dou.ua\/assets\/img\/favicon.ico",
                "id": 1,
                "original_url": "https:\/\/jobs.dou.ua\/companies\/p1k\/vacancies\/106912\/"
            }
        ],
        "thread_ts": "1572683617.465000",
        "parent_user_id": "U6H12P4M7",
        "reactions": [
            {
                "name": "pepe_hmmm",
                "users": [
                    "U99MEKJKH",
                    "U8DEZV7E2",
                    "UB4AGRL3C",
                    "U1LNJJWRG",
                    "U3UMB4R6Y",
                    "U049NHC4X",
                    "UPMCBLT7B",
                    "ULF96QF3K",
                    "UJAHRMQQ7",
                    "ULPRYQNS2"
                ],
                "count": 10
            },
            {
                "name": "male-detective::skin-tone-2",
                "users": [
                    "UFZ9SJ2P3",
                    "UGFMUV1UH",
                    "ULF96QF3K",
                    "U4WGFD012",
                    "UBJ10K86A",
                    "U8AHH35K7",
                    "U1X5Q0S1L"
                ],
                "count": 7
            },
            {
                "name": "triggered",
                "users": [
                    "U6Y47FWKX"
                ],
                "count": 1
            }
        ]
    }
]