[
    {
        "client_msg_id": "1beb3451-ad51-47e8-9887-f2943f4b9e81",
        "type": "message",
        "text": "Всем привет!\n\nНазвание вакансии: Data Engineer.\nНазвание компании: Сиденис.\nГород: Санкт-Петербург, Томск.\n\nОписание того, что нужно делать.\nНеобходимо помочь в организации хранения данных, организации пайплайнов, так чтобы с этими данными можно было удобно работать data scientists. Данные связаны со страховыми контрактами. Структура данных очень разная. Данные будут периодически обновляться.\nРаботать предстоит в распределенной agile команде (Санкт-Петербург, Томск, Цюрих).\n\nТребования:\n1) достаточно хороший разговорный английский\n2) Python\n3) знание математический статистики\n4) разведочный анализ данных\n5) SQL\nПлюсом будет:\n1) ML (потому что возможно в отдаленной перспективе при наличии соответствующих скиллов в команде соответствующие задачи будут переходить от заказчиков к нам)\n2) теория вероятности\n3) желание изучать бизнес-часть задачи, актуарную математику\n4) знание R (может использоваться на проекте на стороне заказчика)\n5) PySpark (потому что он используется на другом проекте для похожих задач)\n\nВот формальная вакансия: <https:\/\/sidenis.ru\/vacancies\/data-engineer>\n\nОзвученная мне вилка: 120000-200000\n\nПлюшки:\n1) белая зарплата\n2) гибкий график, возможность выбрать начало и конец рабочего дня\n3) возможность часть времени работать удаленно\n4) ДМС, в качестве бонуса на выбор возможность оформления ДМС для члена семьи с какого-то момента\n5) бесплатные курсы английского и немецкого",
        "user": "U47HXC0UR",
        "ts": "1585385059.172100",
        "team": "T040HKJE3",
        "user_team": "T040HKJE3",
        "source_team": "T040HKJE3",
        "user_profile": {
            "avatar_hash": "g304c298c67f",
            "image_72": "https:\/\/secure.gravatar.com\/avatar\/1d304c298c67f6a18caeded4e0b5951d.jpg?s=72&d=https%3A%2F%2Fa.slack-edge.com%2Fdf10d%2Fimg%2Favatars%2Fava_0008-72.png",
            "first_name": "Alexey",
            "real_name": "Alexey Osipov",
            "display_name": "alexo",
            "team": "T040HKJE3",
            "name": "alexo",
            "is_restricted": false,
            "is_ultra_restricted": false
        },
        "blocks": [
            {
                "type": "rich_text",
                "block_id": "Q+f",
                "elements": [
                    {
                        "type": "rich_text_section",
                        "elements": [
                            {
                                "type": "text",
                                "text": "Всем привет!\n\nНазвание вакансии: Data Engineer.\nНазвание компании: Сиденис.\nГород: Санкт-Петербург, Томск.\n\nОписание того, что нужно делать.\nНеобходимо помочь в организации хранения данных, организации пайплайнов, так чтобы с этими данными можно было удобно работать data scientists. Данные связаны со страховыми контрактами. Структура данных очень разная. Данные будут периодически обновляться.\nРаботать предстоит в распределенной agile команде (Санкт-Петербург, Томск, Цюрих).\n\nТребования:\n1) достаточно хороший разговорный английский\n2) Python\n3) знание математический статистики\n4) разведочный анализ данных\n5) SQL\nПлюсом будет:\n1) ML (потому что возможно в отдаленной перспективе при наличии соответствующих скиллов в команде соответствующие задачи будут переходить от заказчиков к нам)\n2) теория вероятности\n3) желание изучать бизнес-часть задачи, актуарную математику\n4) знание R (может использоваться на проекте на стороне заказчика)\n5) PySpark (потому что он используется на другом проекте для похожих задач)\n\nВот формальная вакансия: "
                            },
                            {
                                "type": "link",
                                "url": "https:\/\/sidenis.ru\/vacancies\/data-engineer"
                            },
                            {
                                "type": "text",
                                "text": "\n\nОзвученная мне вилка: 120000-200000\n\nПлюшки:\n1) белая зарплата\n2) гибкий график, возможность выбрать начало и конец рабочего дня\n3) возможность часть времени работать удаленно\n4) ДМС, в качестве бонуса на выбор возможность оформления ДМС для члена семьи с какого-то момента\n5) бесплатные курсы английского и немецкого"
                            }
                        ]
                    }
                ]
            }
        ],
        "thread_ts": "1585385059.172100",
        "reply_count": 1,
        "reply_users_count": 1,
        "latest_reply": "1585602832.218600",
        "reply_users": [
            "U47HXC0UR"
        ],
        "replies": [
            {
                "user": "U47HXC0UR",
                "ts": "1585602832.218600"
            }
        ],
        "subscribed": false,
        "reactions": [
            {
                "name": "covid19",
                "users": [
                    "UDSEN1N2E"
                ],
                "count": 1
            }
        ]
    },
    {
        "client_msg_id": "bc3c1916-bac1-4fc0-9214-564d2afb1d8b",
        "type": "message",
        "text": "И ещё одна вакансия:\n\nНазвание вакансии: Data Analyst.\nНазвание компании: Сиденис.\nГород: Томск.\n\nОписание того, что нужно делать.\nВ проекте 5 команд, работающих по скраму. Предстоит присоединиться к одной из них. Эта команда может со временем меняться.\nВсе команды распределенные (на проекте люди из России (Санкт-Петербурга, Томска), Швейцарии, Индии, США).\nЗадачи, как ни странно, будут зависеть от команды.\nОни могут быть такими: анализ результатов работы различных моделей, визуализация результатов, написание скриптов по обработке и анализу данных моделей, написание пакетов. Предстоит писать код на R, его нужно будет знать достаточно хорошо.\n\nТребования:\n1) достаточно хороший разговорный английский\n2) опыт работы с R\n\nПлюсом будет:\n1) знание теории вероятности и математической статистики (для анализа данных и понимания работы моделей)\n2) ML (используется в некоторых командах)\n3) опыт работы с Python (используется для решения определенных задач, возможно придётся столкнуться)\n4) SQL\n5) опыт работы с Java (используется в некоторых командах)\n6) опыт работы с TeX\n\nФормальное описание вакансии: <https:\/\/sidenis.ru\/vacancies\/r-developer>\nОна называется R developer, чтобы подчеркнуть, что нужно достаточно хорошо знать R, и что придётся на нём писать.\n\nОзвученная мне вилка: 80000-140000\n\nПлюшки:\n1) белая зарплата\n2) гибкий график, возможность выбрать начало и конец рабочего дня\n3) возможность часть времени работать удаленно\n4) ДМС, с возможность оформления ДМС для члена семьи с какого-то момента\n5) бесплатные курсы английского и немецкого",
        "user": "U47HXC0UR",
        "ts": "1585385177.173000",
        "team": "T040HKJE3",
        "user_team": "T040HKJE3",
        "source_team": "T040HKJE3",
        "user_profile": {
            "avatar_hash": "g304c298c67f",
            "image_72": "https:\/\/secure.gravatar.com\/avatar\/1d304c298c67f6a18caeded4e0b5951d.jpg?s=72&d=https%3A%2F%2Fa.slack-edge.com%2Fdf10d%2Fimg%2Favatars%2Fava_0008-72.png",
            "first_name": "Alexey",
            "real_name": "Alexey Osipov",
            "display_name": "alexo",
            "team": "T040HKJE3",
            "name": "alexo",
            "is_restricted": false,
            "is_ultra_restricted": false
        },
        "blocks": [
            {
                "type": "rich_text",
                "block_id": "ObT8",
                "elements": [
                    {
                        "type": "rich_text_section",
                        "elements": [
                            {
                                "type": "text",
                                "text": "И ещё одна вакансия:\n\nНазвание вакансии: Data Analyst.\nНазвание компании: Сиденис.\nГород: Томск.\n\nОписание того, что нужно делать.\nВ проекте 5 команд, работающих по скраму. Предстоит присоединиться к одной из них. Эта команда может со временем меняться.\nВсе команды распределенные (на проекте люди из России (Санкт-Петербурга, Томска), Швейцарии, Индии, США).\nЗадачи, как ни странно, будут зависеть от команды.\nОни могут быть такими: анализ результатов работы различных моделей, визуализация результатов, написание скриптов по обработке и анализу данных моделей, написание пакетов. Предстоит писать код на R, его нужно будет знать достаточно хорошо.\n\nТребования:\n1) достаточно хороший разговорный английский\n2) опыт работы с R\n\nПлюсом будет:\n1) знание теории вероятности и математической статистики (для анализа данных и понимания работы моделей)\n2) ML (используется в некоторых командах)\n3) опыт работы с Python (используется для решения определенных задач, возможно придётся столкнуться)\n4) SQL\n5) опыт работы с Java (используется в некоторых командах)\n6) опыт работы с TeX\n\nФормальное описание вакансии: "
                            },
                            {
                                "type": "link",
                                "url": "https:\/\/sidenis.ru\/vacancies\/r-developer"
                            },
                            {
                                "type": "text",
                                "text": "\nОна называется R developer, чтобы подчеркнуть, что нужно достаточно хорошо знать R, и что придётся на нём писать.\n\nОзвученная мне вилка: 80000-140000\n\nПлюшки:\n1) белая зарплата\n2) гибкий график, возможность выбрать начало и конец рабочего дня\n3) возможность часть времени работать удаленно\n4) ДМС, с возможность оформления ДМС для члена семьи с какого-то момента\n5) бесплатные курсы английского и немецкого"
                            }
                        ]
                    }
                ]
            }
        ],
        "thread_ts": "1585385177.173000",
        "reply_count": 6,
        "reply_users_count": 3,
        "latest_reply": "1587914926.142300",
        "reply_users": [
            "UQ9UCJT0T",
            "U47HXC0UR",
            "UMD13056D"
        ],
        "replies": [
            {
                "user": "UQ9UCJT0T",
                "ts": "1585388122.174900"
            },
            {
                "user": "U47HXC0UR",
                "ts": "1585388377.175100"
            },
            {
                "user": "U47HXC0UR",
                "ts": "1585389426.175900"
            },
            {
                "user": "UMD13056D",
                "ts": "1585416235.193000"
            },
            {
                "user": "U47HXC0UR",
                "ts": "1585419393.193200"
            },
            {
                "user": "U47HXC0UR",
                "ts": "1587914926.142300"
            }
        ],
        "subscribed": false,
        "reactions": [
            {
                "name": "joy",
                "users": [
                    "U50GQKH5J",
                    "ULRREQD1Q",
                    "UD6TXA7R7",
                    "UCVT60YSH",
                    "UGZ0UEL5D",
                    "UJG3W0SSZ",
                    "U7E8Y3V19",
                    "UDDCJ9L84"
                ],
                "count": 8
            },
            {
                "name": "notbad",
                "users": [
                    "U50GQKH5J",
                    "UDK41MN5U",
                    "U0Q3USC0Z",
                    "U9LPKKM7X",
                    "U8DEZV7E2",
                    "U27SUBTB9"
                ],
                "count": 6
            },
            {
                "name": "nor",
                "users": [
                    "U4J46N7QU",
                    "U60EETE7N",
                    "U8720JR0U",
                    "UMKQUCV19",
                    "UD6TXA7R7",
                    "UEPUBQ16W",
                    "UD37TP39U",
                    "UJ4QE3VUN",
                    "UM38ES74G",
                    "UC3AL2NKS",
                    "U6URRB952",
                    "UC9HBTUKG",
                    "UKQTPE877",
                    "U9LPKKM7X",
                    "U709XK88H",
                    "UFZ9SJ2P3",
                    "UPD47KCSZ",
                    "UCK2WBKLG",
                    "UJG3W0SSZ",
                    "UJ4QRRNRH",
                    "UDXMNJD4P",
                    "ULPRYQNS2",
                    "UAEBNBWMU",
                    "UQRH33GM8",
                    "UJWEWCC5V",
                    "UCAEKNA4V",
                    "UKQDJU35J",
                    "ULB0VKCET"
                ],
                "count": 28
            },
            {
                "name": "r",
                "users": [
                    "UHR5Q170B",
                    "U47HXC0UR",
                    "U88T71FBL",
                    "UJ4QE3VUN",
                    "U7PHZ3QTU",
                    "UCNNGKT3Q",
                    "U0Q3USC0Z",
                    "U1TJJJZQ8",
                    "U061WBASK",
                    "UCM1WHP1U",
                    "U97HBNVA6",
                    "U24FHECDD",
                    "U29TG6K9U",
                    "U8QCH21HB",
                    "UCMAWD588",
                    "U4N7G9RQA",
                    "U70T87GMA",
                    "U8GPXSE2Z",
                    "U1DT1NDM5",
                    "U8P1RUS9G",
                    "U3D5HVB51",
                    "U9ZA3KF44",
                    "U50GQ7SSK"
                ],
                "count": 23
            },
            {
                "name": "coolstorybob",
                "users": [
                    "ULRREQD1Q",
                    "US2DY7UR5"
                ],
                "count": 2
            },
            {
                "name": "el_resitas_shake2",
                "users": [
                    "UJG3W0SSZ",
                    "UEBC73WP7"
                ],
                "count": 2
            },
            {
                "name": "covid19",
                "users": [
                    "UDSEN1N2E",
                    "UAWDJM48H"
                ],
                "count": 2
            }
        ]
    },
    {
        "client_msg_id": "bf515d58-0138-408c-abe6-fd89bae49d91",
        "type": "message",
        "text": "думаю, и через лет 30 в разделах \"плюшки\" будут писать \"оформление по тк рф\" \/ \"белая зарплата\" :notthisagain:",
        "user": "UQ9UCJT0T",
        "ts": "1585388122.174900",
        "team": "T040HKJE3",
        "user_team": "T040HKJE3",
        "source_team": "T040HKJE3",
        "user_profile": {
            "avatar_hash": "gaf4aae329f4",
            "image_72": "https:\/\/secure.gravatar.com\/avatar\/af4aae329f466fda3cbdff9f35d09b0a.jpg?s=72&d=https%3A%2F%2Fa.slack-edge.com%2Fdf10d%2Fimg%2Favatars%2Fava_0018-72.png",
            "first_name": "NaN",
            "real_name": "NaN",
            "display_name": "NaN",
            "team": "T040HKJE3",
            "name": "p.o.solomin",
            "is_restricted": false,
            "is_ultra_restricted": false
        },
        "blocks": [
            {
                "type": "rich_text",
                "block_id": "\/6B3x",
                "elements": [
                    {
                        "type": "rich_text_section",
                        "elements": [
                            {
                                "type": "text",
                                "text": "думаю, и через лет 30 в разделах \"плюшки\" будут писать \"оформление по тк рф\" \/ \"белая зарплата\" "
                            },
                            {
                                "type": "emoji",
                                "name": "notthisagain"
                            }
                        ]
                    }
                ]
            }
        ],
        "thread_ts": "1585385177.173000",
        "parent_user_id": "U47HXC0UR",
        "reactions": [
            {
                "name": "harold",
                "users": [
                    "UM5DXE4LE",
                    "ULPRYQNS2",
                    "UTB85ATA5"
                ],
                "count": 3
            }
        ]
    },
    {
        "client_msg_id": "a9af3c7e-8bfe-4f84-93bd-7f6b10833426",
        "type": "message",
        "text": "2.5 года назад я работал в одной инвестиционной фирме квонтом. Там у меня была серая зарплата, но я ещё получал часть прибыли от торговых стратегий.\n\nДля меня белая зарплата это плюс :-)",
        "user": "U47HXC0UR",
        "ts": "1585388377.175100",
        "team": "T040HKJE3",
        "user_team": "T040HKJE3",
        "source_team": "T040HKJE3",
        "user_profile": {
            "avatar_hash": "g304c298c67f",
            "image_72": "https:\/\/secure.gravatar.com\/avatar\/1d304c298c67f6a18caeded4e0b5951d.jpg?s=72&d=https%3A%2F%2Fa.slack-edge.com%2Fdf10d%2Fimg%2Favatars%2Fava_0008-72.png",
            "first_name": "Alexey",
            "real_name": "Alexey Osipov",
            "display_name": "alexo",
            "team": "T040HKJE3",
            "name": "alexo",
            "is_restricted": false,
            "is_ultra_restricted": false
        },
        "edited": {
            "user": "U47HXC0UR",
            "ts": "1585389012.000000"
        },
        "blocks": [
            {
                "type": "rich_text",
                "block_id": "lC+q",
                "elements": [
                    {
                        "type": "rich_text_section",
                        "elements": [
                            {
                                "type": "text",
                                "text": "2.5 года назад я работал в одной инвестиционной фирме квонтом. Там у меня была серая зарплата, но я ещё получал часть прибыли от торговых стратегий.\n\nДля меня белая зарплата это плюс :-)"
                            }
                        ]
                    }
                ]
            }
        ],
        "thread_ts": "1585385177.173000",
        "parent_user_id": "U47HXC0UR"
    },
    {
        "client_msg_id": "35fdd503-efe7-4be3-8253-78b30c15f81a",
        "type": "message",
        "text": "Наверное, надо ещё что-нибудь  о компании сказать.\n\nСиденис --- русско-швейцарская IT-компания. Офисы в Цюрихе, Петербурге, Томске, Калининграде. Занимается производством IT-продуктов для различных перестраховочных компаний (Swiss Re, Allianz, ...). Всего в Сиденисе работает около 200 человек.",
        "user": "U47HXC0UR",
        "ts": "1585389426.175900",
        "team": "T040HKJE3",
        "user_team": "T040HKJE3",
        "source_team": "T040HKJE3",
        "user_profile": {
            "avatar_hash": "g304c298c67f",
            "image_72": "https:\/\/secure.gravatar.com\/avatar\/1d304c298c67f6a18caeded4e0b5951d.jpg?s=72&d=https%3A%2F%2Fa.slack-edge.com%2Fdf10d%2Fimg%2Favatars%2Fava_0008-72.png",
            "first_name": "Alexey",
            "real_name": "Alexey Osipov",
            "display_name": "alexo",
            "team": "T040HKJE3",
            "name": "alexo",
            "is_restricted": false,
            "is_ultra_restricted": false
        },
        "blocks": [
            {
                "type": "rich_text",
                "block_id": "ZgyN",
                "elements": [
                    {
                        "type": "rich_text_section",
                        "elements": [
                            {
                                "type": "text",
                                "text": "Наверное, надо ещё что-нибудь  о компании сказать.\n\nСиденис --- русско-швейцарская IT-компания. Офисы в Цюрихе, Петербурге, Томске, Калининграде. Занимается производством IT-продуктов для различных перестраховочных компаний (Swiss Re, Allianz, ...). Всего в Сиденисе работает около 200 человек."
                            }
                        ]
                    }
                ]
            }
        ],
        "thread_ts": "1585385177.173000",
        "parent_user_id": "U47HXC0UR",
        "reactions": [
            {
                "name": "galera",
                "users": [
                    "U9GUF2PN2",
                    "UGZ0UEL5D",
                    "UJG3W0SSZ",
                    "U061WBASK",
                    "ULPRYQNS2"
                ],
                "count": 5
            }
        ]
    },
    {
        "client_msg_id": "aa88d573-5946-422f-b154-3730bbc0de30",
        "type": "message",
        "text": "Для тех, кто тоже не понимает, что происходит:\n<https:\/\/opendatascience.slack.com\/archives\/C04DA5FUF\/p1526210788000104>",
        "user": "UCB3PK96J",
        "ts": "1585393591.185800",
        "team": "T040HKJE3",
        "user_team": "T040HKJE3",
        "source_team": "T040HKJE3",
        "user_profile": {
            "avatar_hash": "g97b560e2057",
            "image_72": "https:\/\/secure.gravatar.com\/avatar\/f897b560e205783ee0ab8f082dee5579.jpg?s=72&d=https%3A%2F%2Fa.slack-edge.com%2Fdf10d%2Fimg%2Favatars%2Fava_0013-72.png",
            "first_name": "Stanislav",
            "real_name": "Stanislav Masharsky",
            "display_name": "dervun",
            "team": "T040HKJE3",
            "name": "masharskyss",
            "is_restricted": false,
            "is_ultra_restricted": false
        },
        "attachments": [
            {
                "from_url": "https:\/\/opendatascience.slack.com\/archives\/C04DA5FUF\/p1526210788000104",
                "fallback": "[May 13th, 2018 4:26 AM] pastafarianist: :thread-please:",
                "ts": "1526210788.000104",
                "author_id": "U04EEBVJ6",
                "author_subname": "Dmitry Nikulin",
                "channel_id": "C04DA5FUF",
                "channel_name": "_jobs",
                "is_msg_unfurl": true,
                "is_thread_root_unfurl": true,
                "text": ":thread-please:",
                "author_name": "Dmitry Nikulin",
                "author_link": "https:\/\/opendatascience.slack.com\/team\/U04EEBVJ6",
                "author_icon": "https:\/\/avatars.slack-edge.com\/2019-08-26\/738586926901_66d7b203db23fc4ce3cb_48.jpg",
                "mrkdwn_in": [
                    "text"
                ],
                "id": 1,
                "original_url": "https:\/\/opendatascience.slack.com\/archives\/C04DA5FUF\/p1526210788000104",
                "footer": "Thread in #_jobs"
            }
        ],
        "blocks": [
            {
                "type": "rich_text",
                "block_id": "edWwZ",
                "elements": [
                    {
                        "type": "rich_text_section",
                        "elements": [
                            {
                                "type": "text",
                                "text": "Для тех, кто тоже не понимает, что происходит:\n"
                            },
                            {
                                "type": "link",
                                "url": "https:\/\/opendatascience.slack.com\/archives\/C04DA5FUF\/p1526210788000104"
                            }
                        ]
                    }
                ]
            }
        ],
        "thread_ts": "1585317535.124600",
        "parent_user_id": "UA2PW0FNK"
    },
    {
        "client_msg_id": "23b15ee0-dc12-44f9-9bca-ae84649a3a93",
        "type": "message",
        "text": "Тут как-то требования с плюсами перепутаны :grimacing:",
        "user": "UMD13056D",
        "ts": "1585416235.193000",
        "team": "T040HKJE3",
        "user_team": "T040HKJE3",
        "source_team": "T040HKJE3",
        "user_profile": {
            "avatar_hash": "33e46340a0f7",
            "image_72": "https:\/\/avatars.slack-edge.com\/2020-07-02\/1218639741282_33e46340a0f7b20e1d09_72.jpg",
            "first_name": "TheBestName",
            "real_name": "TheBestName",
            "display_name": "VodkaBalalayka",
            "team": "T040HKJE3",
            "name": "lyulinanton93",
            "is_restricted": false,
            "is_ultra_restricted": false
        },
        "blocks": [
            {
                "type": "rich_text",
                "block_id": "=It",
                "elements": [
                    {
                        "type": "rich_text_section",
                        "elements": [
                            {
                                "type": "text",
                                "text": "Тут как-то требования с плюсами перепутаны "
                            },
                            {
                                "type": "emoji",
                                "name": "grimacing"
                            }
                        ]
                    }
                ]
            }
        ],
        "thread_ts": "1585385177.173000",
        "parent_user_id": "U47HXC0UR"
    },
    {
        "client_msg_id": "c2dadf3b-d646-410f-817b-a038a5b9b141",
        "type": "message",
        "text": "Нет, не перепутаны. Просто для этой вакансии хотелось в требования ставить только самое основное. То без чего точно ни при каких обстоятельствах нельзя брать. Вот эти 2 пункта и есть: английский и знание R. Особенно учитывая озвученную вилку.\n\nВсё остальное при желании можно будет изучить и получить.",
        "user": "U47HXC0UR",
        "ts": "1585419393.193200",
        "team": "T040HKJE3",
        "user_team": "T040HKJE3",
        "source_team": "T040HKJE3",
        "user_profile": {
            "avatar_hash": "g304c298c67f",
            "image_72": "https:\/\/secure.gravatar.com\/avatar\/1d304c298c67f6a18caeded4e0b5951d.jpg?s=72&d=https%3A%2F%2Fa.slack-edge.com%2Fdf10d%2Fimg%2Favatars%2Fava_0008-72.png",
            "first_name": "Alexey",
            "real_name": "Alexey Osipov",
            "display_name": "alexo",
            "team": "T040HKJE3",
            "name": "alexo",
            "is_restricted": false,
            "is_ultra_restricted": false
        },
        "blocks": [
            {
                "type": "rich_text",
                "block_id": "afR\/",
                "elements": [
                    {
                        "type": "rich_text_section",
                        "elements": [
                            {
                                "type": "text",
                                "text": "Нет, не перепутаны. Просто для этой вакансии хотелось в требования ставить только самое основное. То без чего точно ни при каких обстоятельствах нельзя брать. Вот эти 2 пункта и есть: английский и знание R. Особенно учитывая озвученную вилку.\n\nВсё остальное при желании можно будет изучить и получить."
                            }
                        ]
                    }
                ]
            }
        ],
        "thread_ts": "1585385177.173000",
        "parent_user_id": "U47HXC0UR"
    }
]