[
    {
        "client_msg_id": "74168e1c-913e-49fe-a174-2e2ff75997a4",
        "type": "message",
        "text": "Вакансия: *Software Engineer\\ Разработчик ПО в R’n’D*\n*Компания:* Huawei\n*Департамент :* R’n’D Лаборатория в AI\n*Вилка*: 200-300 тыс RUR в зависимости от уровня\n*Задачи:*\n• Разработка алгоритмов на С++ для обучения нейросетей с использованием CPU\/GPU\/NPU;\n• Вычислительная оптимизация стохастического градиентного спуска для обучения искусственных нейросетей;\n• Внедрение оптимизированных версий AutoML – алгоритмов (HPO, NAS) для серверной инфраструктуры;\nНеобходимая квалификация для позиции:\n• Опыт разработки ПО от 2 лет;\n• Высшее техническое образование;\n• Хорошее знание высшей математики (линейная алгебра, математический анализ);\n• Владение C\/C++(структуры данных, шаблоны проектирования и алгоритмы);\n• Опыт работы с GPU\/CPU, понимание низкоуровневой архитектуры;\n• Знание английского языка не ниже Intermediate;\n*Будет конкуретнтым преимуществом:*\n• Понимание SIMD (ARM NEON и др);\n• Знание Java, Python;\n• Наличие публикаций в научных изданиях;\n• Опыт работы с высоконагруженными\/распределенными системами, параллельная обработка информации;\n• OpenCL\/ Vulkan \/CUDA;\n• Знание одного из DNN фреймворков: Tensorflow, PyTorch,и др;\n• Представление о современных DL моделях : CNN, RNN;\n*Условия:*\n• Оформление согласно ТК РФ;\n• Уютный офис м.Динамо с предстоящим переездом на м. Смоленская (оба офиса в нескольких минутах от метро);\n• Опыт работы в крупнейшей телекоммуникационной компании с возможностями развития;\n• График 5\/2 в офисе, гибкое начало рабочего дня, отсутствие дресс-кода;\n• ДМС со стоматологией для сотрудника и членов семьи.\n_Если тебе интересно, пиши <@UR4UR2B4Z> здесь или в Telegram - я отвечу тебе на все вопросы, если что-то останется - то на них ответит наш тимлид._",
        "user": "UR4UR2B4Z",
        "ts": "1575898348.217700",
        "team": "T040HKJE3",
        "user_team": "T040HKJE3",
        "source_team": "T040HKJE3",
        "user_profile": {
            "avatar_hash": "fd336a3b9ea6",
            "image_72": "https:\/\/avatars.slack-edge.com\/2019-12-08\/856631942625_fd336a3b9ea6bca3f31b_72.jpg",
            "first_name": "Maria",
            "real_name": "Maria Knyazeva",
            "display_name": "zovutmashei",
            "team": "T040HKJE3",
            "name": "knyazeva.mo",
            "is_restricted": false,
            "is_ultra_restricted": false
        },
        "blocks": [
            {
                "type": "rich_text",
                "block_id": "QiFdN",
                "elements": [
                    {
                        "type": "rich_text_section",
                        "elements": [
                            {
                                "type": "text",
                                "text": "Вакансия: "
                            },
                            {
                                "type": "text",
                                "text": "Software Engineer\\ Разработчик ПО в R’n’D",
                                "style": {
                                    "bold": true
                                }
                            },
                            {
                                "type": "text",
                                "text": "\n"
                            },
                            {
                                "type": "text",
                                "text": "Компания:",
                                "style": {
                                    "bold": true
                                }
                            },
                            {
                                "type": "text",
                                "text": " Huawei\n"
                            },
                            {
                                "type": "text",
                                "text": "Департамент : ",
                                "style": {
                                    "bold": true
                                }
                            },
                            {
                                "type": "text",
                                "text": "R’n’D Лаборатория в AI\n"
                            },
                            {
                                "type": "text",
                                "text": "Вилка",
                                "style": {
                                    "bold": true
                                }
                            },
                            {
                                "type": "text",
                                "text": ": 200-300 тыс RUR в зависимости от уровня\n"
                            },
                            {
                                "type": "text",
                                "text": "Задачи:",
                                "style": {
                                    "bold": true
                                }
                            },
                            {
                                "type": "text",
                                "text": "\n• Разработка алгоритмов на С++ для обучения нейросетей с использованием CPU\/GPU\/NPU;\n• Вычислительная оптимизация стохастического градиентного спуска для обучения искусственных нейросетей;\n• Внедрение оптимизированных версий AutoML – алгоритмов (HPO, NAS) для серверной инфраструктуры;\nНеобходимая квалификация для позиции:\n• Опыт разработки ПО от 2 лет;\n• Высшее техническое образование;\n• Хорошее знание высшей математики (линейная алгебра, математический анализ);\n• Владение C\/C++(структуры данных, шаблоны проектирования и алгоритмы);\n• Опыт работы с GPU\/CPU, понимание низкоуровневой архитектуры;\n• Знание английского языка не ниже Intermediate;\n"
                            },
                            {
                                "type": "text",
                                "text": "Будет конкуретнтым преимуществом:",
                                "style": {
                                    "bold": true
                                }
                            },
                            {
                                "type": "text",
                                "text": "\n• Понимание SIMD (ARM NEON и др);\n• Знание Java, Python;\n• Наличие публикаций в научных изданиях;\n• Опыт работы с высоконагруженными\/распределенными системами, параллельная обработка информации;\n• OpenCL\/ Vulkan \/CUDA;\n• Знание одного из DNN фреймворков: Tensorflow, PyTorch,и др;\n• Представление о современных DL моделях : CNN, RNN;\n"
                            },
                            {
                                "type": "text",
                                "text": "Условия:",
                                "style": {
                                    "bold": true
                                }
                            },
                            {
                                "type": "text",
                                "text": "\n• Оформление согласно ТК РФ;\n• Уютный офис м.Динамо с предстоящим переездом на м. Смоленская (оба офиса в нескольких минутах от метро);\n• Опыт работы в крупнейшей телекоммуникационной компании с возможностями развития;\n• График 5\/2 в офисе, гибкое начало рабочего дня, отсутствие дресс-кода;\n• ДМС со стоматологией для сотрудника и членов семьи.\n"
                            },
                            {
                                "type": "text",
                                "text": "Если тебе интересно, пиши ",
                                "style": {
                                    "italic": true
                                }
                            },
                            {
                                "type": "user",
                                "user_id": "UR4UR2B4Z",
                                "style": {
                                    "italic": true
                                }
                            },
                            {
                                "type": "text",
                                "text": " здесь или в Telegram - я отвечу тебе на все вопросы, если что-то останется - то на них ответит наш тимлид.",
                                "style": {
                                    "italic": true
                                }
                            }
                        ]
                    }
                ]
            }
        ],
        "reactions": [
            {
                "name": "popcorn",
                "users": [
                    "UC7CX2SEN",
                    "U705ED0CU",
                    "UG8K6LD6D",
                    "U0FEJNBGQ",
                    "ULA9M7CM9",
                    "UC9HBTUKG",
                    "UFVBUV7QU",
                    "UC9J53NAY",
                    "UJW9M71RV"
                ],
                "count": 9
            }
        ]
    }
]